DESCRIPTION.rst
MANIFEST.in
README.rst
setup.cfg
setup.py
examples/opencl_example.py
examples/opencl_example_job.sh
sigprocge/__init__.py
sigprocge/cl.py
sigprocge.egg-info/PKG-INFO
sigprocge.egg-info/SOURCES.txt
sigprocge.egg-info/dependency_links.txt
sigprocge.egg-info/requires.txt
sigprocge.egg-info/top_level.txt