Metadata-Version: 1.1
Name: sigprocge
Version: 0.2.0
Summary: Python utilities for the SigProC cluster
Home-page: http://github.com/sigproc/python-sigprocge
Author: Rich Wareham
Author-email: rjw57@cam.ac.uk
License: MIT
Keywords: gridengine sigproc cluster
Platform: UNKNOWN
Classifier: Development Status :: 3 - Alpha
Classifier: Intended Audience :: Developers
Classifier: License :: OSI Approved :: MIT License
Classifier: Programming Language :: Python :: 2
Classifier: Programming Language :: Python :: 2.6
Classifier: Programming Language :: Python :: 2.7
Classifier: Programming Language :: Python :: 3
Classifier: Programming Language :: Python :: 3.1
Classifier: Programming Language :: Python :: 3.2
Classifier: Programming Language :: Python :: 3.3
